gigacommitai/__main__.py
gigacommitai/callbacks.py
gigacommitai/cli.py
gigacommitai/cmd/commit.py
gigacommitai/cmd/config.py
gigacommitai/config/__init__.py
gigacommitai/config/schema.py
gigacommitai/git.py
gigacommitai/gpt.py
gigacommitai/runner.py
gigacommitai-1.2.0.dist-info/METADATA
gigacommitai-1.2.0.dist-info/WHEEL
gigacommitai-1.2.0.dist-info/entry_points.txt
gigacommitai-1.2.0.dist-info/RECORD
